[
  {
    "key": "00",
    "title": "00",
    "era": "00",
    "capital": "",
    "summary": "",
    "page": "../pages/Achaemenid-Dynasty.html",
    "dataPath": ""
  },
  {
    "key": "11",
    "title": "11",
    "era": "11",
    "capital": "",
    "summary": "",
    "page": "../pages/Parthian-Dynasty.html",
    "dataPath": "../assets/data/rulers/parthian.json"
  },
  {
    "key": "22",
    "title": "22",
    "era": "22",
    "capital": "",
    "summary": "",
    "page": "../pages/Sasanian-Dynasty.html",
    "dataPath": "../assets/data/rulers/sasanian.json"
  },
  {
    "key": "",
    "title": "",
    "era": "",
    "capital": "",
    "summary": "",
    "page": "../pages/Safavid-Dynasty.html",
    "dataPath": "../assets/data/rulers/safavid.json"
  },
  {
    "key": "",
    "title": "",
    "era": "",
    "capital": "",
    "summary": "",
    "page": "../pages/Afsharid-Dynasty.html",
    "dataPath": "../assets/data/rulers/afsharid.json"
  },
  {
    "key": "zand",
    "title": "",
    "era": "1751–1794",
    "capital": "Shiraz",
    "summary": "Just rule of Karim Khan; arts and trade.",
    "page": "../pages/Zand-Dynasty.html",
    "dataPath": "../assets/data/rulers/zand.json"
  },
  {
    "key": "",
    "title": "",
    "era": "",
    "capital": "Tehran",
    "summary": "Modernization attempts and foreign pressures.",
    "page": "../pages/Qajar-Dynasty.html",
    "dataPath": "../assets/data/rulers/qajar.json"
  },
  {
    "key": "",
    "title": "",
    "era": "00",
    "capital": "T",
    "summary": "State-building and rapid modernization.",
    "page": "../pages/Pahlavi-Dynasty.html",
    "dataPath": "../assets/data/rulers/pahlavi.json"
  },
  {
    "key": "00",
    "title": "00",
    "era": "00",
    "capital": "",
    "summary": "",
    "page": "../pages/Islamic-Republic-of-Iran.htm",
    "dataPath": "../assets/data/rulers/islamic-republic.json"
  }
]
